{
  "clientes": [
    {
      "nombre": "Renzo",
      "empresa": "ette",
      "email": "rloza@ette.biz",
      "telefono": "62402160",
      "notas": "2334324",
      "id": 15
    },
    {
      "nombre": "Renzo",
      "empresa": "ette",
      "email": "rloza@ette.biz",
      "telefono": "62402160",
      "notas": "2334324",
      "id": 17
    },
    {
      "nombre": "Renzo",
      "empresa": "ette",
      "email": "rloza@ette.biz",
      "telefono": "62402160",
      "notas": "2334324",
      "id": 18
    },
    {
      "nombre": "Renzo",
      "empresa": "ette",
      "email": "rloza@ette.biz",
      "telefono": "62402160",
      "notas": "2334324",
      "id": 19
    },
    {
      "nombre": "Renzo",
      "empresa": "ette",
      "email": "rloza@ette.biz",
      "telefono": "62402160",
      "notas": "2334324",
      "id": 20
    },
    {
      "nombre": "Renzo",
      "empresa": "ette",
      "email": "rloza@ette.biz",
      "telefono": "62402160",
      "notas": "2334324",
      "id": 23
    },
    {
      "nombre": "Renzo",
      "empresa": "ette",
      "email": "rloza@ette.biz",
      "telefono": "62402160",
      "notas": "2334324",
      "id": 25
    },
    {
      "nombre": "Juan",
      "empresa": "Codigo con Juan",
      "email": "renzo@juan.com",
      "telefono": "52402323",
      "notas": "HOlas",
      "id": 34
    },
    {
      "nombre": "Juan",
      "empresa": "Codigo con Juan",
      "email": "renzo@juan.com",
      "telefono": "52402323",
      "notas": "HOlas",
      "id": 35
    },
    {
      "nombre": "Renzo",
      "empresa": "ette",
      "email": "rloza@ette.biz",
      "telefono": "62402160",
      "notas": "holas",
      "id": 36
    }
  ]
}